please_help_me_solve/__init__.py
please_help_me_solve/main.py
please_help_me_solve-0.2.dist-info/METADATA
please_help_me_solve-0.2.dist-info/WHEEL
please_help_me_solve-0.2.dist-info/top_level.txt
please_help_me_solve-0.2.dist-info/RECORD
