Metadata-Version: 2.2
Name: please_help_me_solve
Version: 0.2
Requires-Dist: google-generativeai>=0.7.2
Dynamic: description
Dynamic: description-content-type
Dynamic: requires-dist
